sqlalchemy_databricks/__init__.py
sqlalchemy_databricks/_dialect.py
sqlalchemy_databricks-0.1.0.dist-info/entry_points.txt
sqlalchemy_databricks-0.1.0.dist-info/LICENSE.txt
sqlalchemy_databricks-0.1.0.dist-info/WHEEL
sqlalchemy_databricks-0.1.0.dist-info/METADATA
sqlalchemy_databricks-0.1.0.dist-info/RECORD
