Metadata-Version: 2.1
Name: sqlalchemy-databricks
Version: 0.1.0
Summary: SQLAlchemy Dialect for Databricks
Home-page: https://github.com/crflynn/sqlalchemy-databricks
License: MIT
Keywords: databricks,sqlalchemy,dialect
Author: flynn
Author-email: crf204@gmail.com
Requires-Python: >=3.7,<4.0
Classifier: License :: OSI Approved :: MIT License
Classifier: Natural Language :: English
Classifier: Programming Language :: Python :: 3
Classifier: Programming Language :: Python :: 3.10
Classifier: Programming Language :: Python :: 3.7
Classifier: Programming Language :: Python :: 3.8
Classifier: Programming Language :: Python :: 3.9
Classifier: Programming Language :: Python :: Implementation :: CPython
Classifier: Topic :: Database
Classifier: Topic :: Database :: Front-Ends
Requires-Dist: PyHive (>=0,<1)
Requires-Dist: SQLAlchemy (>=1,<2)
Requires-Dist: databricks-sql-connector (>=0,<1)
Project-URL: Documentation, https://github.com/crflynn/sqlalchemy-databricks
Project-URL: Repository, https://github.com/crflynn/sqlalchemy-databricks
